milesianpy/__init__.py
milesianpy/common_operators.py
milesianpy/calculations/__init__.py
milesianpy/calculations/no_variable_calculation.py
milesianpy/error_handling/__init__.py
milesianpy/error_handling/bracket_error.py
milesianpy/error_handling/decimal_error.py
milesianpy/error_handling/invalid_character_error.py
milesianpy/error_handling/operator_error.py
milesianpy/parsers/__init__.py
milesianpy/parsers/basic_parser.py
milesianpy/parsers/number_parser.py
milesianpy/parsers/operator_parser.py
milesianpy-0.0.10.dist-info/METADATA
milesianpy-0.0.10.dist-info/WHEEL
milesianpy-0.0.10.dist-info/top_level.txt
milesianpy-0.0.10.dist-info/RECORD
